[
    {
        "arguments": [
            "-c",
            "-D__GNUC__",
            "-I../Core/Inc",
            "-I../Drivers/STM32F4xx_HAL_Driver/Inc",
            "-I../Drivers/STM32F4xx_HAL_Driver/Inc/Legacy",
            "-I../Drivers/CMSIS/Device/ST/STM32F4xx/Include",
            "-I../Drivers/CMSIS/Include",
            "-I../Application",
            "-I../Application/GM6020",
            "-I../Bsp",
            "-I../Application/Control",
            "-I../Middleware/FreeRTOS/Inc",
            "-I../Middleware/FreeRTOS/Portable",
            "-I../Application/Tasks",
            "-I../Application/Key",
            "-I../Application/DM4310",
            "-DUSE_HAL_DRIVER",
            "-DSTM32F427xx"
        ],
        "directory": "E:/RM/develop/control/6020demo/MDK-ARM",
        "file": "../Core/Src/main.c"
    },
    {
        "arguments": [
            "-c",
            "-D__GNUC__",
            "-I../Core/Inc",
            "-I../Drivers/STM32F4xx_HAL_Driver/Inc",
            "-I../Drivers/STM32F4xx_HAL_Driver/Inc/Legacy",
            "-I../Drivers/CMSIS/Device/ST/STM32F4xx/Include",
            "-I../Drivers/CMSIS/Include",
            "-I../Application",
            "-I../Application/GM6020",
            "-I../Bsp",
            "-I../Application/Control",
            "-I../Middleware/FreeRTOS/Inc",
            "-I../Middleware/FreeRTOS/Portable",
            "-I../Application/Tasks",
            "-I../Application/Key",
            "-I../Application/DM4310",
            "-DUSE_HAL_DRIVER",
            "-DSTM32F427xx"
        ],
        "directory": "E:/RM/develop/control/6020demo/MDK-ARM",
        "file": "../Core/Src/gpio.c"
    },
    {
        "arguments": [
            "-c",
            "-D__GNUC__",
            "-I../Core/Inc",
            "-I../Drivers/STM32F4xx_HAL_Driver/Inc",
            "-I../Drivers/STM32F4xx_HAL_Driver/Inc/Legacy",
            "-I../Drivers/CMSIS/Device/ST/STM32F4xx/Include",
            "-I../Drivers/CMSIS/Include",
            "-I../Application",
            "-I../Application/GM6020",
            "-I../Bsp",
            "-I../Application/Control",
            "-I../Middleware/FreeRTOS/Inc",
            "-I../Middleware/FreeRTOS/Portable",
            "-I../Application/Tasks",
            "-I../Application/Key",
            "-I../Application/DM4310",
            "-DUSE_HAL_DRIVER",
            "-DSTM32F427xx"
        ],
        "directory": "E:/RM/develop/control/6020demo/MDK-ARM",
        "file": "../Core/Src/can.c"
    },
    {
        "arguments": [
            "-c",
            "-D__GNUC__",
            "-I../Core/Inc",
            "-I../Drivers/STM32F4xx_HAL_Driver/Inc",
            "-I../Drivers/STM32F4xx_HAL_Driver/Inc/Legacy",
            "-I../Drivers/CMSIS/Device/ST/STM32F4xx/Include",
            "-I../Drivers/CMSIS/Include",
            "-I../Application",
            "-I../Application/GM6020",
            "-I../Bsp",
            "-I../Application/Control",
            "-I../Middleware/FreeRTOS/Inc",
            "-I../Middleware/FreeRTOS/Portable",
            "-I../Application/Tasks",
            "-I../Application/Key",
            "-I../Application/DM4310",
            "-DUSE_HAL_DRIVER",
            "-DSTM32F427xx"
        ],
        "directory": "E:/RM/develop/control/6020demo/MDK-ARM",
        "file": "../Core/Src/usart.c"
    },
    {
        "arguments": [
            "-c",
            "-D__GNUC__",
            "-I../Core/Inc",
            "-I../Drivers/STM32F4xx_HAL_Driver/Inc",
            "-I../Drivers/STM32F4xx_HAL_Driver/Inc/Legacy",
            "-I../Drivers/CMSIS/Device/ST/STM32F4xx/Include",
            "-I../Drivers/CMSIS/Include",
            "-I../Application",
            "-I../Application/GM6020",
            "-I../Bsp",
            "-I../Application/Control",
            "-I../Middleware/FreeRTOS/Inc",
            "-I../Middleware/FreeRTOS/Portable",
            "-I../Application/Tasks",
            "-I../Application/Key",
            "-I../Application/DM4310",
            "-DUSE_HAL_DRIVER",
            "-DSTM32F427xx"
        ],
        "directory": "E:/RM/develop/control/6020demo/MDK-ARM",
        "file": "../Core/Src/stm32f4xx_it.c"
    },
    {
        "arguments": [
            "-c",
            "-D__GNUC__",
            "-I../Core/Inc",
            "-I../Drivers/STM32F4xx_HAL_Driver/Inc",
            "-I../Drivers/STM32F4xx_HAL_Driver/Inc/Legacy",
            "-I../Drivers/CMSIS/Device/ST/STM32F4xx/Include",
            "-I../Drivers/CMSIS/Include",
            "-I../Application",
            "-I../Application/GM6020",
            "-I../Bsp",
            "-I../Application/Control",
            "-I../Middleware/FreeRTOS/Inc",
            "-I../Middleware/FreeRTOS/Portable",
            "-I../Application/Tasks",
            "-I../Application/Key",
            "-I../Application/DM4310",
            "-DUSE_HAL_DRIVER",
            "-DSTM32F427xx"
        ],
        "directory": "E:/RM/develop/control/6020demo/MDK-ARM",
        "file": "../Core/Src/stm32f4xx_hal_msp.c"
    },
    {
        "arguments": [
            "-c",
            "-D__GNUC__",
            "-I../Core/Inc",
            "-I../Drivers/STM32F4xx_HAL_Driver/Inc",
            "-I../Drivers/STM32F4xx_HAL_Driver/Inc/Legacy",
            "-I../Drivers/CMSIS/Device/ST/STM32F4xx/Include",
            "-I../Drivers/CMSIS/Include",
            "-I../Application",
            "-I../Application/GM6020",
            "-I../Bsp",
            "-I../Application/Control",
            "-I../Middleware/FreeRTOS/Inc",
            "-I../Middleware/FreeRTOS/Portable",
            "-I../Application/Tasks",
            "-I../Application/Key",
            "-I../Application/DM4310",
            "-DUSE_HAL_DRIVER",
            "-DSTM32F427xx"
        ],
        "directory": "E:/RM/develop/control/6020demo/MDK-ARM",
        "file": "../Core/Src/stm32f4xx_hal_timebase_tim.c"
    },
    {
        "arguments": [
            "-c",
            "-D__GNUC__",
            "-I../Core/Inc",
            "-I../Drivers/STM32F4xx_HAL_Driver/Inc",
            "-I../Drivers/STM32F4xx_HAL_Driver/Inc/Legacy",
            "-I../Drivers/CMSIS/Device/ST/STM32F4xx/Include",
            "-I../Drivers/CMSIS/Include",
            "-I../Application",
            "-I../Application/GM6020",
            "-I../Bsp",
            "-I../Application/Control",
            "-I../Middleware/FreeRTOS/Inc",
            "-I../Middleware/FreeRTOS/Portable",
            "-I../Application/Tasks",
            "-I../Application/Key",
            "-I../Application/DM4310",
            "-DUSE_HAL_DRIVER",
            "-DSTM32F427xx"
        ],
        "directory": "E:/RM/develop/control/6020demo/MDK-ARM",
        "file": "../Drivers/STM32F4xx_HAL_Driver/Src/stm32f4xx_hal_tim.c"
    },
    {
        "arguments": [
            "-c",
            "-D__GNUC__",
            "-I../Core/Inc",
            "-I../Drivers/STM32F4xx_HAL_Driver/Inc",
            "-I../Drivers/STM32F4xx_HAL_Driver/Inc/Legacy",
            "-I../Drivers/CMSIS/Device/ST/STM32F4xx/Include",
            "-I../Drivers/CMSIS/Include",
            "-I../Application",
            "-I../Application/GM6020",
            "-I../Bsp",
            "-I../Application/Control",
            "-I../Middleware/FreeRTOS/Inc",
            "-I../Middleware/FreeRTOS/Portable",
            "-I../Application/Tasks",
            "-I../Application/Key",
            "-I../Application/DM4310",
            "-DUSE_HAL_DRIVER",
            "-DSTM32F427xx"
        ],
        "directory": "E:/RM/develop/control/6020demo/MDK-ARM",
        "file": "../Drivers/STM32F4xx_HAL_Driver/Src/stm32f4xx_hal_tim_ex.c"
    },
    {
        "arguments": [
            "-c",
            "-D__GNUC__",
            "-I../Core/Inc",
            "-I../Drivers/STM32F4xx_HAL_Driver/Inc",
            "-I../Drivers/STM32F4xx_HAL_Driver/Inc/Legacy",
            "-I../Drivers/CMSIS/Device/ST/STM32F4xx/Include",
            "-I../Drivers/CMSIS/Include",
            "-I../Application",
            "-I../Application/GM6020",
            "-I../Bsp",
            "-I../Application/Control",
            "-I../Middleware/FreeRTOS/Inc",
            "-I../Middleware/FreeRTOS/Portable",
            "-I../Application/Tasks",
            "-I../Application/Key",
            "-I../Application/DM4310",
            "-DUSE_HAL_DRIVER",
            "-DSTM32F427xx"
        ],
        "directory": "E:/RM/develop/control/6020demo/MDK-ARM",
        "file": "../Drivers/STM32F4xx_HAL_Driver/Src/stm32f4xx_hal_can.c"
    },
    {
        "arguments": [
            "-c",
            "-D__GNUC__",
            "-I../Core/Inc",
            "-I../Drivers/STM32F4xx_HAL_Driver/Inc",
            "-I../Drivers/STM32F4xx_HAL_Driver/Inc/Legacy",
            "-I../Drivers/CMSIS/Device/ST/STM32F4xx/Include",
            "-I../Drivers/CMSIS/Include",
            "-I../Application",
            "-I../Application/GM6020",
            "-I../Bsp",
            "-I../Application/Control",
            "-I../Middleware/FreeRTOS/Inc",
            "-I../Middleware/FreeRTOS/Portable",
            "-I../Application/Tasks",
            "-I../Application/Key",
            "-I../Application/DM4310",
            "-DUSE_HAL_DRIVER",
            "-DSTM32F427xx"
        ],
        "directory": "E:/RM/develop/control/6020demo/MDK-ARM",
        "file": "../Drivers/STM32F4xx_HAL_Driver/Src/stm32f4xx_hal_rcc.c"
    },
    {
        "arguments": [
            "-c",
            "-D__GNUC__",
            "-I../Core/Inc",
            "-I../Drivers/STM32F4xx_HAL_Driver/Inc",
            "-I../Drivers/STM32F4xx_HAL_Driver/Inc/Legacy",
            "-I../Drivers/CMSIS/Device/ST/STM32F4xx/Include",
            "-I../Drivers/CMSIS/Include",
            "-I../Application",
            "-I../Application/GM6020",
            "-I../Bsp",
            "-I../Application/Control",
            "-I../Middleware/FreeRTOS/Inc",
            "-I../Middleware/FreeRTOS/Portable",
            "-I../Application/Tasks",
            "-I../Application/Key",
            "-I../Application/DM4310",
            "-DUSE_HAL_DRIVER",
            "-DSTM32F427xx"
        ],
        "directory": "E:/RM/develop/control/6020demo/MDK-ARM",
        "file": "../Drivers/STM32F4xx_HAL_Driver/Src/stm32f4xx_hal_rcc_ex.c"
    },
    {
        "arguments": [
            "-c",
            "-D__GNUC__",
            "-I../Core/Inc",
            "-I../Drivers/STM32F4xx_HAL_Driver/Inc",
            "-I../Drivers/STM32F4xx_HAL_Driver/Inc/Legacy",
            "-I../Drivers/CMSIS/Device/ST/STM32F4xx/Include",
            "-I../Drivers/CMSIS/Include",
            "-I../Application",
            "-I../Application/GM6020",
            "-I../Bsp",
            "-I../Application/Control",
            "-I../Middleware/FreeRTOS/Inc",
            "-I../Middleware/FreeRTOS/Portable",
            "-I../Application/Tasks",
            "-I../Application/Key",
            "-I../Application/DM4310",
            "-DUSE_HAL_DRIVER",
            "-DSTM32F427xx"
        ],
        "directory": "E:/RM/develop/control/6020demo/MDK-ARM",
        "file": "../Drivers/STM32F4xx_HAL_Driver/Src/stm32f4xx_hal_flash.c"
    },
    {
        "arguments": [
            "-c",
            "-D__GNUC__",
            "-I../Core/Inc",
            "-I../Drivers/STM32F4xx_HAL_Driver/Inc",
            "-I../Drivers/STM32F4xx_HAL_Driver/Inc/Legacy",
            "-I../Drivers/CMSIS/Device/ST/STM32F4xx/Include",
            "-I../Drivers/CMSIS/Include",
            "-I../Application",
            "-I../Application/GM6020",
            "-I../Bsp",
            "-I../Application/Control",
            "-I../Middleware/FreeRTOS/Inc",
            "-I../Middleware/FreeRTOS/Portable",
            "-I../Application/Tasks",
            "-I../Application/Key",
            "-I../Application/DM4310",
            "-DUSE_HAL_DRIVER",
            "-DSTM32F427xx"
        ],
        "directory": "E:/RM/develop/control/6020demo/MDK-ARM",
        "file": "../Drivers/STM32F4xx_HAL_Driver/Src/stm32f4xx_hal_flash_ex.c"
    },
    {
        "arguments": [
            "-c",
            "-D__GNUC__",
            "-I../Core/Inc",
            "-I../Drivers/STM32F4xx_HAL_Driver/Inc",
            "-I../Drivers/STM32F4xx_HAL_Driver/Inc/Legacy",
            "-I../Drivers/CMSIS/Device/ST/STM32F4xx/Include",
            "-I../Drivers/CMSIS/Include",
            "-I../Application",
            "-I../Application/GM6020",
            "-I../Bsp",
            "-I../Application/Control",
            "-I../Middleware/FreeRTOS/Inc",
            "-I../Middleware/FreeRTOS/Portable",
            "-I../Application/Tasks",
            "-I../Application/Key",
            "-I../Application/DM4310",
            "-DUSE_HAL_DRIVER",
            "-DSTM32F427xx"
        ],
        "directory": "E:/RM/develop/control/6020demo/MDK-ARM",
        "file": "../Drivers/STM32F4xx_HAL_Driver/Src/stm32f4xx_hal_flash_ramfunc.c"
    },
    {
        "arguments": [
            "-c",
            "-D__GNUC__",
            "-I../Core/Inc",
            "-I../Drivers/STM32F4xx_HAL_Driver/Inc",
            "-I../Drivers/STM32F4xx_HAL_Driver/Inc/Legacy",
            "-I../Drivers/CMSIS/Device/ST/STM32F4xx/Include",
            "-I../Drivers/CMSIS/Include",
            "-I../Application",
            "-I../Application/GM6020",
            "-I../Bsp",
            "-I../Application/Control",
            "-I../Middleware/FreeRTOS/Inc",
            "-I../Middleware/FreeRTOS/Portable",
            "-I../Application/Tasks",
            "-I../Application/Key",
            "-I../Application/DM4310",
            "-DUSE_HAL_DRIVER",
            "-DSTM32F427xx"
        ],
        "directory": "E:/RM/develop/control/6020demo/MDK-ARM",
        "file": "../Drivers/STM32F4xx_HAL_Driver/Src/stm32f4xx_hal_gpio.c"
    },
    {
        "arguments": [
            "-c",
            "-D__GNUC__",
            "-I../Core/Inc",
            "-I../Drivers/STM32F4xx_HAL_Driver/Inc",
            "-I../Drivers/STM32F4xx_HAL_Driver/Inc/Legacy",
            "-I../Drivers/CMSIS/Device/ST/STM32F4xx/Include",
            "-I../Drivers/CMSIS/Include",
            "-I../Application",
            "-I../Application/GM6020",
            "-I../Bsp",
            "-I../Application/Control",
            "-I../Middleware/FreeRTOS/Inc",
            "-I../Middleware/FreeRTOS/Portable",
            "-I../Application/Tasks",
            "-I../Application/Key",
            "-I../Application/DM4310",
            "-DUSE_HAL_DRIVER",
            "-DSTM32F427xx"
        ],
        "directory": "E:/RM/develop/control/6020demo/MDK-ARM",
        "file": "../Drivers/STM32F4xx_HAL_Driver/Src/stm32f4xx_hal_dma_ex.c"
    },
    {
        "arguments": [
            "-c",
            "-D__GNUC__",
            "-I../Core/Inc",
            "-I../Drivers/STM32F4xx_HAL_Driver/Inc",
            "-I../Drivers/STM32F4xx_HAL_Driver/Inc/Legacy",
            "-I../Drivers/CMSIS/Device/ST/STM32F4xx/Include",
            "-I../Drivers/CMSIS/Include",
            "-I../Application",
            "-I../Application/GM6020",
            "-I../Bsp",
            "-I../Application/Control",
            "-I../Middleware/FreeRTOS/Inc",
            "-I../Middleware/FreeRTOS/Portable",
            "-I../Application/Tasks",
            "-I../Application/Key",
            "-I../Application/DM4310",
            "-DUSE_HAL_DRIVER",
            "-DSTM32F427xx"
        ],
        "directory": "E:/RM/develop/control/6020demo/MDK-ARM",
        "file": "../Drivers/STM32F4xx_HAL_Driver/Src/stm32f4xx_hal_dma.c"
    },
    {
        "arguments": [
            "-c",
            "-D__GNUC__",
            "-I../Core/Inc",
            "-I../Drivers/STM32F4xx_HAL_Driver/Inc",
            "-I../Drivers/STM32F4xx_HAL_Driver/Inc/Legacy",
            "-I../Drivers/CMSIS/Device/ST/STM32F4xx/Include",
            "-I../Drivers/CMSIS/Include",
            "-I../Application",
            "-I../Application/GM6020",
            "-I../Bsp",
            "-I../Application/Control",
            "-I../Middleware/FreeRTOS/Inc",
            "-I../Middleware/FreeRTOS/Portable",
            "-I../Application/Tasks",
            "-I../Application/Key",
            "-I../Application/DM4310",
            "-DUSE_HAL_DRIVER",
            "-DSTM32F427xx"
        ],
        "directory": "E:/RM/develop/control/6020demo/MDK-ARM",
        "file": "../Drivers/STM32F4xx_HAL_Driver/Src/stm32f4xx_hal_pwr.c"
    },
    {
        "arguments": [
            "-c",
            "-D__GNUC__",
            "-I../Core/Inc",
            "-I../Drivers/STM32F4xx_HAL_Driver/Inc",
            "-I../Drivers/STM32F4xx_HAL_Driver/Inc/Legacy",
            "-I../Drivers/CMSIS/Device/ST/STM32F4xx/Include",
            "-I../Drivers/CMSIS/Include",
            "-I../Application",
            "-I../Application/GM6020",
            "-I../Bsp",
            "-I../Application/Control",
            "-I../Middleware/FreeRTOS/Inc",
            "-I../Middleware/FreeRTOS/Portable",
            "-I../Application/Tasks",
            "-I../Application/Key",
            "-I../Application/DM4310",
            "-DUSE_HAL_DRIVER",
            "-DSTM32F427xx"
        ],
        "directory": "E:/RM/develop/control/6020demo/MDK-ARM",
        "file": "../Drivers/STM32F4xx_HAL_Driver/Src/stm32f4xx_hal_pwr_ex.c"
    },
    {
        "arguments": [
            "-c",
            "-D__GNUC__",
            "-I../Core/Inc",
            "-I../Drivers/STM32F4xx_HAL_Driver/Inc",
            "-I../Drivers/STM32F4xx_HAL_Driver/Inc/Legacy",
            "-I../Drivers/CMSIS/Device/ST/STM32F4xx/Include",
            "-I../Drivers/CMSIS/Include",
            "-I../Application",
            "-I../Application/GM6020",
            "-I../Bsp",
            "-I../Application/Control",
            "-I../Middleware/FreeRTOS/Inc",
            "-I../Middleware/FreeRTOS/Portable",
            "-I../Application/Tasks",
            "-I../Application/Key",
            "-I../Application/DM4310",
            "-DUSE_HAL_DRIVER",
            "-DSTM32F427xx"
        ],
        "directory": "E:/RM/develop/control/6020demo/MDK-ARM",
        "file": "../Drivers/STM32F4xx_HAL_Driver/Src/stm32f4xx_hal_cortex.c"
    },
    {
        "arguments": [
            "-c",
            "-D__GNUC__",
            "-I../Core/Inc",
            "-I../Drivers/STM32F4xx_HAL_Driver/Inc",
            "-I../Drivers/STM32F4xx_HAL_Driver/Inc/Legacy",
            "-I../Drivers/CMSIS/Device/ST/STM32F4xx/Include",
            "-I../Drivers/CMSIS/Include",
            "-I../Application",
            "-I../Application/GM6020",
            "-I../Bsp",
            "-I../Application/Control",
            "-I../Middleware/FreeRTOS/Inc",
            "-I../Middleware/FreeRTOS/Portable",
            "-I../Application/Tasks",
            "-I../Application/Key",
            "-I../Application/DM4310",
            "-DUSE_HAL_DRIVER",
            "-DSTM32F427xx"
        ],
        "directory": "E:/RM/develop/control/6020demo/MDK-ARM",
        "file": "../Drivers/STM32F4xx_HAL_Driver/Src/stm32f4xx_hal.c"
    },
    {
        "arguments": [
            "-c",
            "-D__GNUC__",
            "-I../Core/Inc",
            "-I../Drivers/STM32F4xx_HAL_Driver/Inc",
            "-I../Drivers/STM32F4xx_HAL_Driver/Inc/Legacy",
            "-I../Drivers/CMSIS/Device/ST/STM32F4xx/Include",
            "-I../Drivers/CMSIS/Include",
            "-I../Application",
            "-I../Application/GM6020",
            "-I../Bsp",
            "-I../Application/Control",
            "-I../Middleware/FreeRTOS/Inc",
            "-I../Middleware/FreeRTOS/Portable",
            "-I../Application/Tasks",
            "-I../Application/Key",
            "-I../Application/DM4310",
            "-DUSE_HAL_DRIVER",
            "-DSTM32F427xx"
        ],
        "directory": "E:/RM/develop/control/6020demo/MDK-ARM",
        "file": "../Drivers/STM32F4xx_HAL_Driver/Src/stm32f4xx_hal_exti.c"
    },
    {
        "arguments": [
            "-c",
            "-D__GNUC__",
            "-I../Core/Inc",
            "-I../Drivers/STM32F4xx_HAL_Driver/Inc",
            "-I../Drivers/STM32F4xx_HAL_Driver/Inc/Legacy",
            "-I../Drivers/CMSIS/Device/ST/STM32F4xx/Include",
            "-I../Drivers/CMSIS/Include",
            "-I../Application",
            "-I../Application/GM6020",
            "-I../Bsp",
            "-I../Application/Control",
            "-I../Middleware/FreeRTOS/Inc",
            "-I../Middleware/FreeRTOS/Portable",
            "-I../Application/Tasks",
            "-I../Application/Key",
            "-I../Application/DM4310",
            "-DUSE_HAL_DRIVER",
            "-DSTM32F427xx"
        ],
        "directory": "E:/RM/develop/control/6020demo/MDK-ARM",
        "file": "../Drivers/STM32F4xx_HAL_Driver/Src/stm32f4xx_hal_uart.c"
    },
    {
        "arguments": [
            "-c",
            "-D__GNUC__",
            "-I../Core/Inc",
            "-I../Drivers/STM32F4xx_HAL_Driver/Inc",
            "-I../Drivers/STM32F4xx_HAL_Driver/Inc/Legacy",
            "-I../Drivers/CMSIS/Device/ST/STM32F4xx/Include",
            "-I../Drivers/CMSIS/Include",
            "-I../Application",
            "-I../Application/GM6020",
            "-I../Bsp",
            "-I../Application/Control",
            "-I../Middleware/FreeRTOS/Inc",
            "-I../Middleware/FreeRTOS/Portable",
            "-I../Application/Tasks",
            "-I../Application/Key",
            "-I../Application/DM4310",
            "-DUSE_HAL_DRIVER",
            "-DSTM32F427xx"
        ],
        "directory": "E:/RM/develop/control/6020demo/MDK-ARM",
        "file": "../Core/Src/system_stm32f4xx.c"
    },
    {
        "arguments": [
            "-c",
            "-D__GNUC__",
            "-I../Core/Inc",
            "-I../Drivers/STM32F4xx_HAL_Driver/Inc",
            "-I../Drivers/STM32F4xx_HAL_Driver/Inc/Legacy",
            "-I../Drivers/CMSIS/Device/ST/STM32F4xx/Include",
            "-I../Drivers/CMSIS/Include",
            "-I../Application",
            "-I../Application/GM6020",
            "-I../Bsp",
            "-I../Application/Control",
            "-I../Middleware/FreeRTOS/Inc",
            "-I../Middleware/FreeRTOS/Portable",
            "-I../Application/Tasks",
            "-I../Application/Key",
            "-I../Application/DM4310",
            "-DUSE_HAL_DRIVER",
            "-DSTM32F427xx"
        ],
        "directory": "E:/RM/develop/control/6020demo/MDK-ARM",
        "file": "../Application/GM6020/GM6020.c"
    },
    {
        "arguments": [
            "-c",
            "-D__GNUC__",
            "-I../Core/Inc",
            "-I../Drivers/STM32F4xx_HAL_Driver/Inc",
            "-I../Drivers/STM32F4xx_HAL_Driver/Inc/Legacy",
            "-I../Drivers/CMSIS/Device/ST/STM32F4xx/Include",
            "-I../Drivers/CMSIS/Include",
            "-I../Application",
            "-I../Application/GM6020",
            "-I../Bsp",
            "-I../Application/Control",
            "-I../Middleware/FreeRTOS/Inc",
            "-I../Middleware/FreeRTOS/Portable",
            "-I../Application/Tasks",
            "-I../Application/Key",
            "-I../Application/DM4310",
            "-DUSE_HAL_DRIVER",
            "-DSTM32F427xx"
        ],
        "directory": "E:/RM/develop/control/6020demo/MDK-ARM",
        "file": "../Bsp/bsp_can.c"
    },
    {
        "arguments": [
            "-c",
            "-D__GNUC__",
            "-I../Core/Inc",
            "-I../Drivers/STM32F4xx_HAL_Driver/Inc",
            "-I../Drivers/STM32F4xx_HAL_Driver/Inc/Legacy",
            "-I../Drivers/CMSIS/Device/ST/STM32F4xx/Include",
            "-I../Drivers/CMSIS/Include",
            "-I../Application",
            "-I../Application/GM6020",
            "-I../Bsp",
            "-I../Application/Control",
            "-I../Middleware/FreeRTOS/Inc",
            "-I../Middleware/FreeRTOS/Portable",
            "-I../Application/Tasks",
            "-I../Application/Key",
            "-I../Application/DM4310",
            "-DUSE_HAL_DRIVER",
            "-DSTM32F427xx"
        ],
        "directory": "E:/RM/develop/control/6020demo/MDK-ARM",
        "file": "../Application/Control/PID.c"
    },
    {
        "arguments": [
            "-c",
            "-D__GNUC__",
            "-I../Core/Inc",
            "-I../Drivers/STM32F4xx_HAL_Driver/Inc",
            "-I../Drivers/STM32F4xx_HAL_Driver/Inc/Legacy",
            "-I../Drivers/CMSIS/Device/ST/STM32F4xx/Include",
            "-I../Drivers/CMSIS/Include",
            "-I../Application",
            "-I../Application/GM6020",
            "-I../Bsp",
            "-I../Application/Control",
            "-I../Middleware/FreeRTOS/Inc",
            "-I../Middleware/FreeRTOS/Portable",
            "-I../Application/Tasks",
            "-I../Application/Key",
            "-I../Application/DM4310",
            "-DUSE_HAL_DRIVER",
            "-DSTM32F427xx"
        ],
        "directory": "E:/RM/develop/control/6020demo/MDK-ARM",
        "file": "../Middleware/FreeRTOS/Src/croutine.c"
    },
    {
        "arguments": [
            "-c",
            "-D__GNUC__",
            "-I../Core/Inc",
            "-I../Drivers/STM32F4xx_HAL_Driver/Inc",
            "-I../Drivers/STM32F4xx_HAL_Driver/Inc/Legacy",
            "-I../Drivers/CMSIS/Device/ST/STM32F4xx/Include",
            "-I../Drivers/CMSIS/Include",
            "-I../Application",
            "-I../Application/GM6020",
            "-I../Bsp",
            "-I../Application/Control",
            "-I../Middleware/FreeRTOS/Inc",
            "-I../Middleware/FreeRTOS/Portable",
            "-I../Application/Tasks",
            "-I../Application/Key",
            "-I../Application/DM4310",
            "-DUSE_HAL_DRIVER",
            "-DSTM32F427xx"
        ],
        "directory": "E:/RM/develop/control/6020demo/MDK-ARM",
        "file": "../Middleware/FreeRTOS/Src/event_groups.c"
    },
    {
        "arguments": [
            "-c",
            "-D__GNUC__",
            "-I../Core/Inc",
            "-I../Drivers/STM32F4xx_HAL_Driver/Inc",
            "-I../Drivers/STM32F4xx_HAL_Driver/Inc/Legacy",
            "-I../Drivers/CMSIS/Device/ST/STM32F4xx/Include",
            "-I../Drivers/CMSIS/Include",
            "-I../Application",
            "-I../Application/GM6020",
            "-I../Bsp",
            "-I../Application/Control",
            "-I../Middleware/FreeRTOS/Inc",
            "-I../Middleware/FreeRTOS/Portable",
            "-I../Application/Tasks",
            "-I../Application/Key",
            "-I../Application/DM4310",
            "-DUSE_HAL_DRIVER",
            "-DSTM32F427xx"
        ],
        "directory": "E:/RM/develop/control/6020demo/MDK-ARM",
        "file": "../Middleware/FreeRTOS/Src/list.c"
    },
    {
        "arguments": [
            "-c",
            "-D__GNUC__",
            "-I../Core/Inc",
            "-I../Drivers/STM32F4xx_HAL_Driver/Inc",
            "-I../Drivers/STM32F4xx_HAL_Driver/Inc/Legacy",
            "-I../Drivers/CMSIS/Device/ST/STM32F4xx/Include",
            "-I../Drivers/CMSIS/Include",
            "-I../Application",
            "-I../Application/GM6020",
            "-I../Bsp",
            "-I../Application/Control",
            "-I../Middleware/FreeRTOS/Inc",
            "-I../Middleware/FreeRTOS/Portable",
            "-I../Application/Tasks",
            "-I../Application/Key",
            "-I../Application/DM4310",
            "-DUSE_HAL_DRIVER",
            "-DSTM32F427xx"
        ],
        "directory": "E:/RM/develop/control/6020demo/MDK-ARM",
        "file": "../Middleware/FreeRTOS/Src/queue.c"
    },
    {
        "arguments": [
            "-c",
            "-D__GNUC__",
            "-I../Core/Inc",
            "-I../Drivers/STM32F4xx_HAL_Driver/Inc",
            "-I../Drivers/STM32F4xx_HAL_Driver/Inc/Legacy",
            "-I../Drivers/CMSIS/Device/ST/STM32F4xx/Include",
            "-I../Drivers/CMSIS/Include",
            "-I../Application",
            "-I../Application/GM6020",
            "-I../Bsp",
            "-I../Application/Control",
            "-I../Middleware/FreeRTOS/Inc",
            "-I../Middleware/FreeRTOS/Portable",
            "-I../Application/Tasks",
            "-I../Application/Key",
            "-I../Application/DM4310",
            "-DUSE_HAL_DRIVER",
            "-DSTM32F427xx"
        ],
        "directory": "E:/RM/develop/control/6020demo/MDK-ARM",
        "file": "../Middleware/FreeRTOS/Src/stream_buffer.c"
    },
    {
        "arguments": [
            "-c",
            "-D__GNUC__",
            "-I../Core/Inc",
            "-I../Drivers/STM32F4xx_HAL_Driver/Inc",
            "-I../Drivers/STM32F4xx_HAL_Driver/Inc/Legacy",
            "-I../Drivers/CMSIS/Device/ST/STM32F4xx/Include",
            "-I../Drivers/CMSIS/Include",
            "-I../Application",
            "-I../Application/GM6020",
            "-I../Bsp",
            "-I../Application/Control",
            "-I../Middleware/FreeRTOS/Inc",
            "-I../Middleware/FreeRTOS/Portable",
            "-I../Application/Tasks",
            "-I../Application/Key",
            "-I../Application/DM4310",
            "-DUSE_HAL_DRIVER",
            "-DSTM32F427xx"
        ],
        "directory": "E:/RM/develop/control/6020demo/MDK-ARM",
        "file": "../Middleware/FreeRTOS/Src/tasks.c"
    },
    {
        "arguments": [
            "-c",
            "-D__GNUC__",
            "-I../Core/Inc",
            "-I../Drivers/STM32F4xx_HAL_Driver/Inc",
            "-I../Drivers/STM32F4xx_HAL_Driver/Inc/Legacy",
            "-I../Drivers/CMSIS/Device/ST/STM32F4xx/Include",
            "-I../Drivers/CMSIS/Include",
            "-I../Application",
            "-I../Application/GM6020",
            "-I../Bsp",
            "-I../Application/Control",
            "-I../Middleware/FreeRTOS/Inc",
            "-I../Middleware/FreeRTOS/Portable",
            "-I../Application/Tasks",
            "-I../Application/Key",
            "-I../Application/DM4310",
            "-DUSE_HAL_DRIVER",
            "-DSTM32F427xx"
        ],
        "directory": "E:/RM/develop/control/6020demo/MDK-ARM",
        "file": "../Middleware/FreeRTOS/Src/timers.c"
    },
    {
        "arguments": [
            "-c",
            "-D__GNUC__",
            "-I../Core/Inc",
            "-I../Drivers/STM32F4xx_HAL_Driver/Inc",
            "-I../Drivers/STM32F4xx_HAL_Driver/Inc/Legacy",
            "-I../Drivers/CMSIS/Device/ST/STM32F4xx/Include",
            "-I../Drivers/CMSIS/Include",
            "-I../Application",
            "-I../Application/GM6020",
            "-I../Bsp",
            "-I../Application/Control",
            "-I../Middleware/FreeRTOS/Inc",
            "-I../Middleware/FreeRTOS/Portable",
            "-I../Application/Tasks",
            "-I../Application/Key",
            "-I../Application/DM4310",
            "-DUSE_HAL_DRIVER",
            "-DSTM32F427xx"
        ],
        "directory": "E:/RM/develop/control/6020demo/MDK-ARM",
        "file": "../Middleware/FreeRTOS/Portable/heap_4.c"
    },
    {
        "arguments": [
            "-c",
            "-D__GNUC__",
            "-I../Core/Inc",
            "-I../Drivers/STM32F4xx_HAL_Driver/Inc",
            "-I../Drivers/STM32F4xx_HAL_Driver/Inc/Legacy",
            "-I../Drivers/CMSIS/Device/ST/STM32F4xx/Include",
            "-I../Drivers/CMSIS/Include",
            "-I../Application",
            "-I../Application/GM6020",
            "-I../Bsp",
            "-I../Application/Control",
            "-I../Middleware/FreeRTOS/Inc",
            "-I../Middleware/FreeRTOS/Portable",
            "-I../Application/Tasks",
            "-I../Application/Key",
            "-I../Application/DM4310",
            "-DUSE_HAL_DRIVER",
            "-DSTM32F427xx"
        ],
        "directory": "E:/RM/develop/control/6020demo/MDK-ARM",
        "file": "../Middleware/FreeRTOS/Portable/port.c"
    },
    {
        "arguments": [
            "-c",
            "-D__GNUC__",
            "-I../Core/Inc",
            "-I../Drivers/STM32F4xx_HAL_Driver/Inc",
            "-I../Drivers/STM32F4xx_HAL_Driver/Inc/Legacy",
            "-I../Drivers/CMSIS/Device/ST/STM32F4xx/Include",
            "-I../Drivers/CMSIS/Include",
            "-I../Application",
            "-I../Application/GM6020",
            "-I../Bsp",
            "-I../Application/Control",
            "-I../Middleware/FreeRTOS/Inc",
            "-I../Middleware/FreeRTOS/Portable",
            "-I../Application/Tasks",
            "-I../Application/Key",
            "-I../Application/DM4310",
            "-DUSE_HAL_DRIVER",
            "-DSTM32F427xx"
        ],
        "directory": "E:/RM/develop/control/6020demo/MDK-ARM",
        "file": "../Application/Tasks/RobotTask.c"
    },
    {
        "arguments": [
            "-c",
            "-D__GNUC__",
            "-I../Core/Inc",
            "-I../Drivers/STM32F4xx_HAL_Driver/Inc",
            "-I../Drivers/STM32F4xx_HAL_Driver/Inc/Legacy",
            "-I../Drivers/CMSIS/Device/ST/STM32F4xx/Include",
            "-I../Drivers/CMSIS/Include",
            "-I../Application",
            "-I../Application/GM6020",
            "-I../Bsp",
            "-I../Application/Control",
            "-I../Middleware/FreeRTOS/Inc",
            "-I../Middleware/FreeRTOS/Portable",
            "-I../Application/Tasks",
            "-I../Application/Key",
            "-I../Application/DM4310",
            "-DUSE_HAL_DRIVER",
            "-DSTM32F427xx"
        ],
        "directory": "E:/RM/develop/control/6020demo/MDK-ARM",
        "file": "../Application/Key/Key.c"
    },
    {
        "arguments": [
            "-c",
            "-D__GNUC__",
            "-I../Core/Inc",
            "-I../Drivers/STM32F4xx_HAL_Driver/Inc",
            "-I../Drivers/STM32F4xx_HAL_Driver/Inc/Legacy",
            "-I../Drivers/CMSIS/Device/ST/STM32F4xx/Include",
            "-I../Drivers/CMSIS/Include",
            "-I../Application",
            "-I../Application/GM6020",
            "-I../Bsp",
            "-I../Application/Control",
            "-I../Middleware/FreeRTOS/Inc",
            "-I../Middleware/FreeRTOS/Portable",
            "-I../Application/Tasks",
            "-I../Application/Key",
            "-I../Application/DM4310",
            "-DUSE_HAL_DRIVER",
            "-DSTM32F427xx"
        ],
        "directory": "E:/RM/develop/control/6020demo/MDK-ARM",
        "file": "../Application/DM4310/DM4310.c"
    }
]